{
    "f105e207-b132-dc7a-889f-9bff2826862d": {
        "paletteKey": "FlexLayoutCol",
        "commentid": null,
        "designerReference": [
            {
                "_key": "componentLabel",
                "_value": "Column",
                "_type": "kv",
                "_attrDef": "p",
                "_useAsLabel": true
            },
            {
                "_key": "style",
                "_value": "",
                "_type": "kv",
                "_attrDef": "p"
            },
            {
                "_key": "class",
                "_value": [
                    "kg-full-width"
                ],
                "_type": "dav",
                "_attrDef": "p"
            },
            {
                "_key": "fxFlex",
                "_value": "",
                "_type": "kv",
                "_attrDef": "p"
            },
            {
                "_key": "fxLayoutGap",
                "_value": "",
                "_type": "kv",
                "_attrDef": "p"
            },
            {
                "_key": "wrap",
                "_value": "wrap",
                "_type": "a",
                "_attrDef": "p"
            },
            {
                "_key": "layoutAlign",
                "_value": "start",
                "_type": "a",
                "_attrDef": "p"
            },
            {
                "_key": "pLayoutAlign",
                "_value": "stretch",
                "_type": "a",
                "_attrDef": "p"
            },
            {
                "_key": "[fxShow]",
                "_value": "true",
                "_type": "kv",
                "_attrDef": "p"
            }
        ],
        "d0114dc8-356f-2961-1e31-00c2e86d3d74": {
            "paletteKey": "FlexLayoutRow",
            "parentEditorKey": "f105e207-b132-dc7a-889f-9bff2826862d",
            "commentid": null,
            "designerReference": [
                {
                    "_key": "componentLabel",
                    "_value": "Row",
                    "_type": "kv",
                    "_attrDef": "p",
                    "_useAsLabel": true
                },
                {
                    "_key": "style",
                    "_value": "",
                    "_type": "kv",
                    "_attrDef": "p"
                },
                {
                    "_key": "class",
                    "_value": "",
                    "_type": "dav",
                    "_attrDef": "p"
                },
                {
                    "_key": "fxFlex",
                    "_value": "",
                    "_type": "kv",
                    "_attrDef": "p"
                },
                {
                    "_key": "fxLayoutGap",
                    "_value": "",
                    "_type": "kv",
                    "_attrDef": "p"
                },
                {
                    "_key": "wrap",
                    "_value": "wrap",
                    "_type": "a",
                    "_attrDef": "p"
                },
                {
                    "_key": "layoutAlign",
                    "_value": "center",
                    "_type": "a",
                    "_attrDef": "p"
                },
                {
                    "_key": "pLayoutAlign",
                    "_value": "center",
                    "_type": "a",
                    "_attrDef": "p"
                },
                {
                    "_key": "[fxShow]",
                    "_value": "true",
                    "_type": "kv",
                    "_attrDef": "p"
                }
            ],
            "10ec247e-c496-5b64-7023-eac4cc30175c": {
                "paletteKey": "FlexLayoutCol",
                "parentEditorKey": "d0114dc8-356f-2961-1e31-00c2e86d3d74",
                "commentid": null,
                "designerReference": [
                    {
                        "_key": "componentLabel",
                        "_value": "Column",
                        "_type": "kv",
                        "_attrDef": "p",
                        "_useAsLabel": true
                    },
                    {
                        "_key": "style",
                        "_value": "",
                        "_type": "kv",
                        "_attrDef": "p"
                    },
                    {
                        "_key": "class",
                        "_value": "",
                        "_type": "dav",
                        "_attrDef": "p"
                    },
                    {
                        "_key": "fxFlex",
                        "_value": "",
                        "_type": "kv",
                        "_attrDef": "p"
                    },
                    {
                        "_key": "fxLayoutGap",
                        "_value": "",
                        "_type": "kv",
                        "_attrDef": "p"
                    },
                    {
                        "_key": "wrap",
                        "_value": "wrap",
                        "_type": "a",
                        "_attrDef": "p"
                    },
                    {
                        "_key": "layoutAlign",
                        "_value": "start",
                        "_type": "a",
                        "_attrDef": "p"
                    },
                    {
                        "_key": "pLayoutAlign",
                        "_value": "stretch",
                        "_type": "a",
                        "_attrDef": "p"
                    },
                    {
                        "_key": "[fxShow]",
                        "_value": "true",
                        "_type": "kv",
                        "_attrDef": "p"
                    }
                ],
                "1526d148-fb68-7210-24c7-60ef5837df6c": {
                    "paletteKey": "Html5",
                    "parentEditorKey": "10ec247e-c496-5b64-7023-eac4cc30175c",
                    "isAdvancedComponent": true,
                    "commentid": null,
                    "designerReference": [
                        {
                            "_key": "style",
                            "_value": "",
                            "_type": "kv",
                            "_attrDef": "p"
                        },
                        {
                            "_key": "class",
                            "_value": "",
                            "_type": "dav",
                            "_attrDef": "p"
                        },
                        {
                            "_key": "htmlElement",
                            "_value": "h3",
                            "_type": "dav",
                            "_attrDef": "p",
                            "_useAsLabel": true
                        },
                        {
                            "_key": "tagType",
                            "_value": "h3",
                            "_type": "a",
                            "_attrDef": "p",
                            "_visibility": false
                        },
                        {
                            "_key": "name",
                            "_value": "",
                            "_type": "kv",
                            "_attrDef": "p",
                            "_visibility": false
                        },
                        {
                            "_key": "sandbox",
                            "_value": "",
                            "_type": "kv",
                            "_attrDef": "p",
                            "_visibility": false
                        },
                        {
                            "_key": "src",
                            "_value": "",
                            "_type": "kv",
                            "_attrDef": "p",
                            "_visibility": false
                        },
                        {
                            "_key": "srcdoc",
                            "_value": "",
                            "_type": "kv",
                            "_attrDef": "p",
                            "_visibility": false
                        },
                        {
                            "_key": "width",
                            "_value": "",
                            "_type": "kv",
                            "_attrDef": "p",
                            "_visibility": false
                        },
                        {
                            "_key": "[autoplay]",
                            "_value": "",
                            "_type": "kv",
                            "_attrDef": "p",
                            "_visibility": false
                        },
                        {
                            "_key": "[loop]",
                            "_value": "",
                            "_type": "kv",
                            "_attrDef": "p",
                            "_visibility": false
                        },
                        {
                            "_key": "data",
                            "_value": "",
                            "_type": "kv",
                            "_attrDef": "p",
                            "_visibility": false
                        },
                        {
                            "_key": "audioSource",
                            "_value": [],
                            "_type": "a",
                            "_attrDef": "p",
                            "_visibility": false
                        },
                        {
                            "_key": "videoSource",
                            "_value": [],
                            "_type": "a",
                            "_attrDef": "p",
                            "_visibility": false
                        },
                        {
                            "_key": "audioDatasource",
                            "_value": "",
                            "_type": "a",
                            "_attrDef": "p",
                            "_visibility": false
                        },
                        {
                            "_key": "audioSrc",
                            "_value": "",
                            "_type": "a",
                            "_attrDef": "p",
                            "_visibility": false
                        },
                        {
                            "_key": "audioType",
                            "_value": "",
                            "_type": "a",
                            "_attrDef": "p",
                            "_visibility": false
                        },
                        {
                            "_key": "videoDatasource",
                            "_value": "",
                            "_type": "a",
                            "_attrDef": "p",
                            "_visibility": false
                        },
                        {
                            "_key": "videoSrc",
                            "_value": "",
                            "_type": "a",
                            "_attrDef": "p",
                            "_visibility": false
                        },
                        {
                            "_key": "videoType",
                            "_value": "",
                            "_type": "a",
                            "_attrDef": "p",
                            "_visibility": false
                        },
                        {
                            "_key": "(audioplay)",
                            "_value": "",
                            "_type": "a",
                            "_attrDef": "p",
                            "_visibility": false
                        },
                        {
                            "_key": "(videoplay)",
                            "_value": "",
                            "_type": "a",
                            "_attrDef": "p",
                            "_visibility": false
                        },
                        {
                            "_key": "(audiopause)",
                            "_value": "",
                            "_type": "kv",
                            "_attrDef": "p",
                            "_visibility": false
                        },
                        {
                            "_key": "(videopause)",
                            "_value": "",
                            "_type": "kv",
                            "_attrDef": "p",
                            "_visibility": false
                        },
                        {
                            "_key": "(audioended)",
                            "_value": "",
                            "_type": "kv",
                            "_attrDef": "p",
                            "_visibility": false
                        },
                        {
                            "_key": "(videoended)",
                            "_value": "",
                            "_type": "kv",
                            "_attrDef": "p",
                            "_visibility": false
                        }
                    ],
                    "928936d9-1409-d4d9-0086-44c3e134b15c": {
                        "paletteKey": "html-editor",
                        "parentEditorKey": "1526d148-fb68-7210-24c7-60ef5837df6c",
                        "isAdvancedChildComponent": true,
                        "commentid": null,
                        "designerReference": [
                            {
                                "_key": "style",
                                "_value": "",
                                "_type": "kv",
                                "_attrDef": "p"
                            },
                            {
                                "_key": "class",
                                "_value": "",
                                "_type": "dav",
                                "_attrDef": "p"
                            },
                            {
                                "_key": "html",
                                "_value": "Enter Reason:",
                                "_type": "a",
                                "_attrDef": "p"
                            }
                        ]
                    }
                }
            }
        },
        "717466c0-6dd2-9c62-e692-f413cc5a9f81": {
            "paletteKey": "FlexLayoutRow",
            "parentEditorKey": "f105e207-b132-dc7a-889f-9bff2826862d",
            "commentid": null,
            "designerReference": [
                {
                    "_key": "componentLabel",
                    "_value": "Row",
                    "_type": "kv",
                    "_attrDef": "p",
                    "_useAsLabel": true
                },
                {
                    "_key": "style",
                    "_value": "",
                    "_type": "kv",
                    "_attrDef": "p"
                },
                {
                    "_key": "class",
                    "_value": "",
                    "_type": "dav",
                    "_attrDef": "p"
                },
                {
                    "_key": "fxFlex",
                    "_value": "",
                    "_type": "kv",
                    "_attrDef": "p"
                },
                {
                    "_key": "fxLayoutGap",
                    "_value": "",
                    "_type": "kv",
                    "_attrDef": "p"
                },
                {
                    "_key": "wrap",
                    "_value": "wrap",
                    "_type": "a",
                    "_attrDef": "p"
                },
                {
                    "_key": "layoutAlign",
                    "_value": "center",
                    "_type": "a",
                    "_attrDef": "p"
                },
                {
                    "_key": "pLayoutAlign",
                    "_value": "center",
                    "_type": "a",
                    "_attrDef": "p"
                },
                {
                    "_key": "[fxShow]",
                    "_value": "true",
                    "_type": "kv",
                    "_attrDef": "p"
                }
            ],
            "d1f63a34-2a09-206a-119d-8ce1a5e9809d": {
                "paletteKey": "FlexLayoutCol",
                "parentEditorKey": "717466c0-6dd2-9c62-e692-f413cc5a9f81",
                "commentid": null,
                "designerReference": [
                    {
                        "_key": "componentLabel",
                        "_value": "Column",
                        "_type": "kv",
                        "_attrDef": "p",
                        "_useAsLabel": true
                    },
                    {
                        "_key": "style",
                        "_value": "",
                        "_type": "kv",
                        "_attrDef": "p"
                    },
                    {
                        "_key": "class",
                        "_value": [
                            "kg-full-width"
                        ],
                        "_type": "dav",
                        "_attrDef": "p"
                    },
                    {
                        "_key": "fxFlex",
                        "_value": "",
                        "_type": "kv",
                        "_attrDef": "p"
                    },
                    {
                        "_key": "fxLayoutGap",
                        "_value": "",
                        "_type": "kv",
                        "_attrDef": "p"
                    },
                    {
                        "_key": "wrap",
                        "_value": "wrap",
                        "_type": "a",
                        "_attrDef": "p"
                    },
                    {
                        "_key": "layoutAlign",
                        "_value": "start",
                        "_type": "a",
                        "_attrDef": "p"
                    },
                    {
                        "_key": "pLayoutAlign",
                        "_value": "stretch",
                        "_type": "a",
                        "_attrDef": "p"
                    },
                    {
                        "_key": "[fxShow]",
                        "_value": "true",
                        "_type": "kv",
                        "_attrDef": "p"
                    }
                ],
                "0c0c2796-c52e-057d-f8c8-2f3eda50310e": {
                    "paletteKey": "NG-Form",
                    "parentEditorKey": "d1f63a34-2a09-206a-119d-8ce1a5e9809d",
                    "commentid": null,
                    "designerReference": [
                        {
                            "_key": "componentLabel",
                            "_value": "Form",
                            "_type": "kv",
                            "_attrDef": "p",
                            "_useAsLabel": true
                        },
                        {
                            "_key": "style",
                            "_value": "",
                            "_type": "kv",
                            "_attrDef": "p"
                        },
                        {
                            "_key": "class",
                            "_value": "",
                            "_type": "dav",
                            "_attrDef": "p"
                        },
                        {
                            "_key": "action",
                            "_value": "",
                            "_type": "kv",
                            "_attrDef": "p"
                        },
                        {
                            "_key": "method",
                            "_value": "",
                            "_type": "kv",
                            "_attrDef": "p"
                        },
                        {
                            "_key": "target",
                            "_value": "",
                            "_type": "kv",
                            "_attrDef": "p"
                        },
                        {
                            "_key": "(ngSubmit)",
                            "_value": "",
                            "_type": "kv",
                            "_attrDef": "p"
                        },
                        {
                            "_key": "(reset)",
                            "_value": "",
                            "_type": "kv",
                            "_attrDef": "p"
                        },
                        {
                            "_key": "[formGroup]",
                            "_value": "page.claimReasonForm",
                            "_type": "kv",
                            "_attrDef": "c"
                        }
                    ],
                    "dc6c2bee-f437-fa0f-9ce2-128c0ddac837": {
                        "paletteKey": "NG-TextArea",
                        "parentEditorKey": "0c0c2796-c52e-057d-f8c8-2f3eda50310e",
                        "commentid": null,
                        "designerReference": [
                            {
                                "_key": "style",
                                "_value": "",
                                "_type": "kv",
                                "_attrDef": "p"
                            },
                            {
                                "_key": "class",
                                "_value": [
                                    "kg-full-width"
                                ],
                                "_type": "dav",
                                "_attrDef": "p"
                            },
                            {
                                "_key": "placeholder",
                                "_value": "Text Area",
                                "_type": "kv",
                                "_attrDef": "p",
                                "_useAsLabel": true
                            },
                            {
                                "_key": "value",
                                "_value": "",
                                "_type": "kv",
                                "_attrDef": "p"
                            },
                            {
                                "_key": "[required]",
                                "_value": "false",
                                "_type": "kv",
                                "_attrDef": "p"
                            },
                            {
                                "_key": "[appearance]",
                                "_value": "",
                                "_type": "kv",
                                "_attrDef": "p"
                            },
                            {
                                "_key": "Label",
                                "_value": "",
                                "_type": "a",
                                "_attrDef": "p"
                            },
                            {
                                "_key": "[floatLabel]",
                                "_value": "'auto'",
                                "_type": "kv",
                                "_attrDef": "p"
                            },
                            {
                                "_key": "[(ngModel)]",
                                "_value": "",
                                "_type": "kv",
                                "_attrDef": "p"
                            },
                            {
                                "_key": "color",
                                "_value": "",
                                "_type": "kv",
                                "_attrDef": "p"
                            },
                            {
                                "_key": "name",
                                "_value": "",
                                "_type": "kv",
                                "_attrDef": "p"
                            },
                            {
                                "_key": "[readonly]",
                                "_value": "",
                                "_type": "kv",
                                "_attrDef": "p"
                            },
                            {
                                "_key": "[disabled]",
                                "_value": "",
                                "_type": "kv",
                                "_attrDef": "p"
                            },
                            {
                                "_key": "formControlName",
                                "_value": "reason",
                                "_type": "kv",
                                "_attrDef": "c"
                            }
                        ]
                    }
                }
            }
        },
        "983a5e44-7a43-711f-2fd8-17efeba6e441": {
            "paletteKey": "FlexLayoutRow",
            "parentEditorKey": "f105e207-b132-dc7a-889f-9bff2826862d",
            "commentid": null,
            "designerReference": [
                {
                    "_key": "componentLabel",
                    "_value": "Row",
                    "_type": "kv",
                    "_attrDef": "p",
                    "_useAsLabel": true
                },
                {
                    "_key": "style",
                    "_value": "",
                    "_type": "kv",
                    "_attrDef": "p"
                },
                {
                    "_key": "class",
                    "_value": "",
                    "_type": "dav",
                    "_attrDef": "p"
                },
                {
                    "_key": "fxFlex",
                    "_value": "",
                    "_type": "kv",
                    "_attrDef": "p"
                },
                {
                    "_key": "fxLayoutGap",
                    "_value": "",
                    "_type": "kv",
                    "_attrDef": "p"
                },
                {
                    "_key": "wrap",
                    "_value": "wrap",
                    "_type": "a",
                    "_attrDef": "p"
                },
                {
                    "_key": "layoutAlign",
                    "_value": "center",
                    "_type": "a",
                    "_attrDef": "p"
                },
                {
                    "_key": "pLayoutAlign",
                    "_value": "center",
                    "_type": "a",
                    "_attrDef": "p"
                },
                {
                    "_key": "[fxShow]",
                    "_value": "true",
                    "_type": "kv",
                    "_attrDef": "p"
                }
            ],
            "6e99a33a-96a3-aa88-22ac-c49776c3f152": {
                "paletteKey": "FlexLayoutCol",
                "parentEditorKey": "983a5e44-7a43-711f-2fd8-17efeba6e441",
                "commentid": null,
                "designerReference": [
                    {
                        "_key": "componentLabel",
                        "_value": "Login Button",
                        "_type": "kv",
                        "_attrDef": "p",
                        "_useAsLabel": true
                    },
                    {
                        "_key": "style",
                        "_value": "",
                        "_type": "kv",
                        "_attrDef": "p"
                    },
                    {
                        "_key": "class",
                        "_value": [
                            "logclaim-btn",
                            "relative"
                        ],
                        "_type": "dav",
                        "_attrDef": "p"
                    },
                    {
                        "_key": "fxFlex",
                        "_value": "",
                        "_type": "kv",
                        "_attrDef": "p"
                    },
                    {
                        "_key": "fxLayoutGap",
                        "_value": "",
                        "_type": "kv",
                        "_attrDef": "p"
                    },
                    {
                        "_key": "wrap",
                        "_value": "wrap",
                        "_type": "a",
                        "_attrDef": "p"
                    },
                    {
                        "_key": "layoutAlign",
                        "_value": "start",
                        "_type": "a",
                        "_attrDef": "p"
                    },
                    {
                        "_key": "pLayoutAlign",
                        "_value": "stretch",
                        "_type": "a",
                        "_attrDef": "p"
                    },
                    {
                        "_key": "[fxShow]",
                        "_value": "true",
                        "_type": "kv",
                        "_attrDef": "p"
                    },
                    {
                        "_key": "(click)",
                        "_value": "submitReason(page.claimReasonForm)",
                        "_type": "kv",
                        "_attrDef": "c",
                        "objValue": {
                            "nodeID": "sd_KYMMjBWOQl3atc0u",
                            "functionName": "submitReason",
                            "activeTree": "pages",
                            "z": "sd_BcfQ7HWdDjhV9OJ2",
                            "input": [
                                "page.claimReasonForm"
                            ]
                        }
                    }
                ],
                "54e84d44-1dc2-187d-cc22-a8828e5d9854": {
                    "paletteKey": "FlexLayoutCol",
                    "parentEditorKey": "6e99a33a-96a3-aa88-22ac-c49776c3f152",
                    "commentid": null,
                    "designerReference": [
                        {
                            "_key": "componentLabel",
                            "_value": "Column",
                            "_type": "kv",
                            "_attrDef": "p",
                            "_useAsLabel": true
                        },
                        {
                            "_key": "style",
                            "_value": "top: -6px; left: -4px",
                            "_type": "kv",
                            "_attrDef": "p"
                        },
                        {
                            "_key": "class",
                            "_value": [
                                "stylish-btn",
                                "absolute"
                            ],
                            "_type": "dav",
                            "_attrDef": "p"
                        },
                        {
                            "_key": "fxFlex",
                            "_value": "",
                            "_type": "kv",
                            "_attrDef": "p"
                        },
                        {
                            "_key": "fxLayoutGap",
                            "_value": "",
                            "_type": "kv",
                            "_attrDef": "p"
                        },
                        {
                            "_key": "wrap",
                            "_value": "wrap",
                            "_type": "a",
                            "_attrDef": "p"
                        },
                        {
                            "_key": "layoutAlign",
                            "_value": "center",
                            "_type": "a",
                            "_attrDef": "p"
                        },
                        {
                            "_key": "pLayoutAlign",
                            "_value": "center",
                            "_type": "a",
                            "_attrDef": "p"
                        },
                        {
                            "_key": "[fxShow]",
                            "_value": "true",
                            "_type": "kv",
                            "_attrDef": "p"
                        }
                    ],
                    "edf1eb31-adf7-a47f-965b-158d9203fb88": {
                        "paletteKey": "Html5",
                        "parentEditorKey": "54e84d44-1dc2-187d-cc22-a8828e5d9854",
                        "isAdvancedComponent": true,
                        "commentid": null,
                        "designerReference": [
                            {
                                "_key": "style",
                                "_value": "",
                                "_type": "kv",
                                "_attrDef": "p"
                            },
                            {
                                "_key": "class",
                                "_value": "",
                                "_type": "dav",
                                "_attrDef": "p"
                            },
                            {
                                "_key": "htmlElement",
                                "_value": "div",
                                "_type": "dav",
                                "_attrDef": "p",
                                "_useAsLabel": true
                            },
                            {
                                "_key": "tagType",
                                "_value": "",
                                "_type": "a",
                                "_attrDef": "p",
                                "_visibility": false
                            },
                            {
                                "_key": "name",
                                "_value": "",
                                "_type": "kv",
                                "_attrDef": "p",
                                "_visibility": false
                            },
                            {
                                "_key": "sandbox",
                                "_value": "",
                                "_type": "kv",
                                "_attrDef": "p",
                                "_visibility": false
                            },
                            {
                                "_key": "src",
                                "_value": "",
                                "_type": "kv",
                                "_attrDef": "p",
                                "_visibility": false
                            },
                            {
                                "_key": "srcdoc",
                                "_value": "",
                                "_type": "kv",
                                "_attrDef": "p",
                                "_visibility": false
                            },
                            {
                                "_key": "width",
                                "_value": "",
                                "_type": "kv",
                                "_attrDef": "p",
                                "_visibility": false
                            },
                            {
                                "_key": "[autoplay]",
                                "_value": "",
                                "_type": "kv",
                                "_attrDef": "p",
                                "_visibility": false
                            },
                            {
                                "_key": "[loop]",
                                "_value": "",
                                "_type": "kv",
                                "_attrDef": "p",
                                "_visibility": false
                            },
                            {
                                "_key": "data",
                                "_value": "",
                                "_type": "kv",
                                "_attrDef": "p",
                                "_visibility": false
                            },
                            {
                                "_key": "audioSource",
                                "_value": [],
                                "_type": "a",
                                "_attrDef": "p",
                                "_visibility": false
                            },
                            {
                                "_key": "videoSource",
                                "_value": [],
                                "_type": "a",
                                "_attrDef": "p",
                                "_visibility": false
                            },
                            {
                                "_key": "audioDatasource",
                                "_value": "",
                                "_type": "a",
                                "_attrDef": "p",
                                "_visibility": false
                            },
                            {
                                "_key": "audioSrc",
                                "_value": "",
                                "_type": "a",
                                "_attrDef": "p",
                                "_visibility": false
                            },
                            {
                                "_key": "audioType",
                                "_value": "",
                                "_type": "a",
                                "_attrDef": "p",
                                "_visibility": false
                            },
                            {
                                "_key": "videoDatasource",
                                "_value": "",
                                "_type": "a",
                                "_attrDef": "p",
                                "_visibility": false
                            },
                            {
                                "_key": "videoSrc",
                                "_value": "",
                                "_type": "a",
                                "_attrDef": "p",
                                "_visibility": false
                            },
                            {
                                "_key": "videoType",
                                "_value": "",
                                "_type": "a",
                                "_attrDef": "p",
                                "_visibility": false
                            },
                            {
                                "_key": "(audioplay)",
                                "_value": "",
                                "_type": "a",
                                "_attrDef": "p",
                                "_visibility": false
                            },
                            {
                                "_key": "(videoplay)",
                                "_value": "",
                                "_type": "a",
                                "_attrDef": "p",
                                "_visibility": false
                            },
                            {
                                "_key": "(audiopause)",
                                "_value": "",
                                "_type": "kv",
                                "_attrDef": "p",
                                "_visibility": false
                            },
                            {
                                "_key": "(videopause)",
                                "_value": "",
                                "_type": "kv",
                                "_attrDef": "p",
                                "_visibility": false
                            },
                            {
                                "_key": "(audioended)",
                                "_value": "",
                                "_type": "kv",
                                "_attrDef": "p",
                                "_visibility": false
                            },
                            {
                                "_key": "(videoended)",
                                "_value": "",
                                "_type": "kv",
                                "_attrDef": "p",
                                "_visibility": false
                            }
                        ],
                        "20e02780-af14-daa7-bc0c-127b0ab78f48": {
                            "paletteKey": "html-editor",
                            "parentEditorKey": "edf1eb31-adf7-a47f-965b-158d9203fb88",
                            "isAdvancedChildComponent": true,
                            "commentid": null,
                            "designerReference": [
                                {
                                    "_key": "style",
                                    "_value": "",
                                    "_type": "kv",
                                    "_attrDef": "p"
                                },
                                {
                                    "_key": "class",
                                    "_value": "",
                                    "_type": "dav",
                                    "_attrDef": "p"
                                },
                                {
                                    "_key": "html",
                                    "_value": "Submit Reason",
                                    "_type": "a",
                                    "_attrDef": "p"
                                }
                            ]
                        }
                    }
                }
            },
            "269baaa2-abeb-7e2a-9b9d-117d26b7c8c8": {
                "paletteKey": "FlexLayoutCol",
                "parentEditorKey": "983a5e44-7a43-711f-2fd8-17efeba6e441",
                "isCommented": "true",
                "commentid": "1725557505369",
                "designerReference": [
                    {
                        "_key": "componentLabel",
                        "_value": "Column",
                        "_type": "kv",
                        "_attrDef": "p",
                        "_useAsLabel": true
                    },
                    {
                        "_key": "style",
                        "_value": "",
                        "_type": "kv",
                        "_attrDef": "p"
                    },
                    {
                        "_key": "class",
                        "_value": "",
                        "_type": "dav",
                        "_attrDef": "p"
                    },
                    {
                        "_key": "fxFlex",
                        "_value": "",
                        "_type": "kv",
                        "_attrDef": "p"
                    },
                    {
                        "_key": "fxLayoutGap",
                        "_value": "",
                        "_type": "kv",
                        "_attrDef": "p"
                    },
                    {
                        "_key": "wrap",
                        "_value": "wrap",
                        "_type": "a",
                        "_attrDef": "p"
                    },
                    {
                        "_key": "layoutAlign",
                        "_value": "start",
                        "_type": "a",
                        "_attrDef": "p"
                    },
                    {
                        "_key": "pLayoutAlign",
                        "_value": "stretch",
                        "_type": "a",
                        "_attrDef": "p"
                    },
                    {
                        "_key": "[fxShow]",
                        "_value": "true",
                        "_type": "kv",
                        "_attrDef": "p"
                    }
                ],
                "5851a7c0-c57a-cdce-e5f7-c664dee3f576": {
                    "paletteKey": "NG-RaisedButton",
                    "parentEditorKey": "269baaa2-abeb-7e2a-9b9d-117d26b7c8c8",
                    "isCommented": "true",
                    "commentid": "1725557505369",
                    "designerReference": [
                        {
                            "_key": "style",
                            "_value": "",
                            "_type": "kv",
                            "_attrDef": "p"
                        },
                        {
                            "_key": "class",
                            "_value": "",
                            "_type": "dav",
                            "_attrDef": "p"
                        },
                        {
                            "_key": "buttonname",
                            "_value": "Search",
                            "_type": "a",
                            "_attrDef": "p",
                            "_useAsLabel": true
                        },
                        {
                            "_key": "color",
                            "_value": "accent",
                            "_type": "kv",
                            "_attrDef": "p"
                        },
                        {
                            "_key": "(click)",
                            "_value": "find()",
                            "_type": "kv",
                            "_attrDef": "p",
                            "objValue": {
                                "nodeID": "sd_rU0R3WzeGLC0CJEH",
                                "functionName": "find",
                                "activeTree": "pages",
                                "z": "sd_DhHQUCCXlUUb7ZvE",
                                "input": []
                            }
                        },
                        {
                            "_key": "[disabled]",
                            "_value": "",
                            "_type": "kv",
                            "_attrDef": "p"
                        },
                        {
                            "_key": "[disableRipple]",
                            "_value": "",
                            "_type": "kv",
                            "_attrDef": "p"
                        },
                        {
                            "_key": "type",
                            "_value": "",
                            "_type": "kv",
                            "_attrDef": "p"
                        },
                        {
                            "_key": "routerLink",
                            "_value": "",
                            "_type": "kv",
                            "_attrDef": "p"
                        }
                    ]
                }
            }
        }
    }
}
